batterytender/__init__.py
batterytender-1.2.0.dist-info/LICENSE
batterytender-1.2.0.dist-info/METADATA
batterytender-1.2.0.dist-info/WHEEL
batterytender-1.2.0.dist-info/top_level.txt
batterytender-1.2.0.dist-info/RECORD
