Metadata-Version: 2.1
Name: batterytender
Version: 1.2.0
Summary: Python API for talking to the Deltran Battery Tender API
Home-page: https://github.com/jkoelker/batterytender/
Author: Jason Kölker
Author-email: jason@koelker.net
License: MIT
Keywords: deltran battery tender batterytender
Platform: UNKNOWN
Requires-Dist: requests (>=1.0.0)
Requires-Dist: ttldict
Requires-Dist: python-dateutil
